elspice.py
elspice-0.0.1.dist-info/LICENSE
elspice-0.0.1.dist-info/METADATA
elspice-0.0.1.dist-info/WHEEL
elspice-0.0.1.dist-info/top_level.txt
elspice-0.0.1.dist-info/RECORD
