Metadata-Version: 2.1
Name: elspice
Version: 0.0.1
Summary: Efficient Language - Simulation Program with Integrated Circuit Emphasis
Author-email: Ali Hakim Taskiran <alihakimxyz@gmail.com>
License: GNU GENERAL PUBLIC LICENSE
Project-URL: Homepage, https://github.com/alihakimtaskiran/elspice
Project-URL: Bug Tracker, https://github.com/alihakimtaskiran/elspice/issues
Classifier: Programming Language :: Python :: 3
Classifier: License :: OSI Approved :: GNU General Public License v3 (GPLv3)
Classifier: Operating System :: OS Independent
Requires-Python: >=3.7
License-File: LICENSE
